<?xml version="1.0" encoding="utf-8"?>
<entries>
  <entry time="2013-09-08T12:06:52.5677434Z" id="3dae9dc5-eb88-437c-81e7-a5092baa7ff2" type="0">
    <message>Updating branch 'b07636b2a9b348ed49b29dc268120c274df6a478'.</message>
  </entry>
  <entry time="2013-09-08T12:06:52.8970089Z" id="cabfbf6f-f965-40ef-9803-65feb1c4d9ea" type="0">
    <message>Updating submodules.</message>
  </entry>
  <entry time="2013-09-08T12:06:52.9308533Z" id="fdc9b478-13f2-4c02-b4eb-e218f96650c7" type="0">
    <message>Preparing deployment for commit id 'b07636b2a9'.</message>
  </entry>
  <entry time="2013-09-08T12:06:53.0559258Z" id="9deaad86-6f9a-4e87-9c9f-2f68f747c61c" type="0">
    <message>Generating deployment script.</message>
    <entry time="2013-09-08T12:06:53.0871103Z" id="a33c0af9-37d3-49e2-ad38-31f1d8cf8257" type="0">
      <message>Using cached version of deployment script (command: 'azure -y --no-dot-deployment -r "C:\DWASFiles\Sites\draft-table\VirtualDirectory0\site\repository" -o "C:\DWASFiles\Sites\draft-table\VirtualDirectory0\site\deployments\tools" --node --sitePath "C:\DWASFiles\Sites\draft-table\VirtualDirectory0\site\repository"').</message>
    </entry>
  </entry>
  <entry time="2013-09-08T12:06:53.1184154Z" id="3d75bb09-7c36-46e1-b668-a071fa31eaeb" type="0">
    <message>Running deployment command...</message>
    <entry time="2013-09-08T12:06:53.1340386Z" id="35aeba6a-548f-48c6-ac68-f3e63995bed9" type="0">
      <message>Command: C:\DWASFiles\Sites\draft-table\VirtualDirectory0\site\deployments\tools\deploy.cmd</message>
    </entry>
    <entry time="2013-09-08T12:06:53.4933523Z" id="8c9cfe05-7e28-4464-9117-4e6fab8b6a93" type="0">
      <message>Handling node.js deployment.</message>
    </entry>
    <entry time="2013-09-08T12:06:53.7902268Z" id="4a484974-3ee6-4836-a38a-f7d3d7842bab" type="0">
      <message>KuduSync.NET from: 'C:\DWASFiles\Sites\draft-table\VirtualDirectory0\site\repository' to: 'C:\DWASFiles\Sites\draft-table\VirtualDirectory0\site\wwwroot'</message>
    </entry>
    <entry time="2013-09-08T12:06:53.9777141Z" id="fb25633e-d1c2-44d9-9b4b-6ce43f5ded95" type="0">
      <message>The package.json file does not specify node.js engine version constraints.</message>
    </entry>
    <entry time="2013-09-08T12:06:53.9777141Z" id="a259dffa-e4f5-4bf6-b609-4b636fef6dce" type="0">
      <message>The node.js application will run with the default node.js version 0.10.5.</message>
    </entry>
    <entry time="2013-09-08T12:06:55.6339223Z" id="15683563-bf53-4dba-ab53-9cc4f1f40846" type="0">
      <message>Finished successfully.</message>
    </entry>
  </entry>
  <entry time="2013-09-08T12:06:55.6652239Z" id="5b0726df-dcf5-480f-a1fd-4be53cae411d" type="0">
    <message>Deployment successful.</message>
  </entry>
</entries>