<?xml version="1.0" encoding="utf-8"?>
<deployment>
  <id>3b8ada548fb5f5602fd0b038e4effe38fc6fa4b2</id>
  <author>Ian Sibner</author>
  <deployer>$draft-table</deployer>
  <authorEmail>sibnerian@gmail.com</authorEmail>
  <message>    Merge branch 'master' of github.com:tomshen/changememaybe
</message>
  <progress></progress>
  <status>Success</status>
  <statusText></statusText>
  <lastSuccessEndTime>2013-09-08T12:41:42.6185137Z</lastSuccessEndTime>
  <receivedTime>2013-09-08T12:39:25.0304431Z</receivedTime>
  <startTime>2013-09-08T12:41:40.0692015Z</startTime>
  <endTime>2013-09-08T12:41:42.6185137Z</endTime>
  <complete>True</complete>
  <is_temp>False</is_temp>
  <is_readonly>False</is_readonly>
</deployment>